README.rst
setup.cfg
setup.py
lambdazen/__init__.py
lambdazen/lambdazen.py
lambdazen.egg-info/PKG-INFO
lambdazen.egg-info/SOURCES.txt
lambdazen.egg-info/dependency_links.txt
lambdazen.egg-info/not-zip-safe
lambdazen.egg-info/top_level.txt