Metadata-Version: 1.0
Name: lambdazen
Version: 0.1.5
Summary: Syntax changes for python lambdas.
Home-page: http://github.com/brthornbury/lambdazen
Author: Bryan Thornbury
Author-email: author@example.com
License: MIT
Platform: UNKNOWN
